empirelang/__init__.py
empirelang-0.1.0.1.dist-info/WHEEL
empirelang-0.1.0.1.dist-info/METADATA
empirelang-0.1.0.1.dist-info/RECORD
