Metadata-Version: 2.1
Name: empirelang
Version: 0.1.0.1
Summary: The Empire language
Author: What_do_we_do_now
Requires-Python: >=3.8,<4.0
Classifier: Programming Language :: Python :: 3
Classifier: Programming Language :: Python :: 3.10
Classifier: Programming Language :: Python :: 3.8
Classifier: Programming Language :: Python :: 3.9
